tocxer/__init__.py
tocxer-1.0.1.dist-info/METADATA
tocxer-1.0.1.dist-info/WHEEL
tocxer-1.0.1.dist-info/top_level.txt
tocxer-1.0.1.dist-info/RECORD
