Metadata-Version: 2.4
Name: tocxer
Version: 1.0.1
Summary: print(函数)
Author: Gtl
Author-email: vvvmcvvv@163.com
Dynamic: author
Dynamic: author-email
Dynamic: summary
